aioopenexchangerates/__init__.py
aioopenexchangerates/client.py
aioopenexchangerates/exceptions.py
aioopenexchangerates/model/__init__.py
aioopenexchangerates/model/latest.py
aioopenexchangerates/model/response.py
aioopenexchangerates/py.typed
aioopenexchangerates-0.6.20.dist-info/LICENSE
aioopenexchangerates-0.6.20.dist-info/METADATA
aioopenexchangerates-0.6.20.dist-info/WHEEL
aioopenexchangerates-0.6.20.dist-info/RECORD
