Metadata-Version: 2.3
Name: aioopenexchangerates
Version: 0.6.20
Summary: Fetch rates from openexchangerates with aiohttp.
License: Apache-2.0
Author: Martin Hjelmare
Author-email: marhje52@gmail.com
Requires-Python: >=3.11,<4.0
Classifier: Development Status :: 2 - Pre-Alpha
Classifier: Intended Audience :: Developers
Classifier: License :: OSI Approved :: Apache Software License
Classifier: Natural Language :: English
Classifier: Operating System :: OS Independent
Classifier: Programming Language :: Python :: 3
Classifier: Programming Language :: Python :: 3.11
Classifier: Programming Language :: Python :: 3.12
Classifier: Programming Language :: Python :: 3.13
Classifier: Topic :: Software Development :: Libraries
Requires-Dist: aiohttp (>=3.8.4,<4.0.0)
Requires-Dist: mashumaro (>=3.13.1,<4.0.0)
Project-URL: Bug Tracker, https://github.com/MartinHjelmare/aioopenexchangerates/issues
Project-URL: Changelog, https://github.com/MartinHjelmare/aioopenexchangerates/blob/main/CHANGELOG.md
Project-URL: Documentation, https://aioopenexchangerates.readthedocs.io
Project-URL: Repository, https://github.com/MartinHjelmare/aioopenexchangerates
